xl_tables/__init__.py
xl_tables/__meta__.py
xl_tables/dtypes.py
xl_tables/fields.py
xl_tables/prop_utils.py
xl_tables/openpyxl_support/__init__.py
xl_tables/openpyxl_support/constants.py
xl_tables/openpyxl_support/csv_utils.py
xl_tables/openpyxl_support/fake_excel.py
xl_tables/openpyxl_support/table.py
xl_tables/openpyxl_support/workbook.py
xl_tables/windows/__init__.py
xl_tables/windows/constants.py
xl_tables/windows/excel_attributes.py
xl_tables/windows/read_file_details.py
xl_tables/windows/table.py
xl_tables-2.0.0.dist-info/METADATA
xl_tables-2.0.0.dist-info/WHEEL
xl_tables-2.0.0.dist-info/licenses/LICENSE
xl_tables-2.0.0.dist-info/RECORD
