Metadata-Version: 2.4
Name: xl_tables
Version: 2.0.0
Summary: Read and write excel files using table descriptors.
Project-URL: Repository, https://github.com/justengel/xl_tables
Author-email: Justin Engel <jtengel08@gmail.com>
License: MIT License
License-File: LICENSE
Keywords: csv,database,excel,xls,xlsx
Classifier: Development Status :: 4 - Beta
Classifier: Intended Audience :: Developers
Classifier: License :: OSI Approved :: MIT License
Classifier: Programming Language :: Python :: 3
Classifier: Programming Language :: Python :: 3.13
Classifier: Topic :: Software Development :: Build Tools
Requires-Python: >=3.13
Requires-Dist: dynamicmethod>=1.1.0
Requires-Dist: openpyxl>=3.1.5
Requires-Dist: wrapt>=1.13.3
Provides-Extra: windows
Requires-Dist: pywin32>=227; extra == 'windows'
